membrain/__init__.py
membrain-0.0.1.dist-info/METADATA
membrain-0.0.1.dist-info/WHEEL
membrain-0.0.1.dist-info/RECORD
