Metadata-Version: 2.4
Name: membrain
Version: 0.0.1
Summary: membrane protein localization for cryo-ET
Project-URL: homepage, https://github.com/CellArchLab/MemBrain-v2
Project-URL: repository, https://github.com/CellArchLab/MemBrain-v2
Author-email: Lorenz Lamm <lorenz.lamm@helmholtz-munich.de>
License: BSD 3-Clause License
Classifier: Development Status :: 3 - Alpha
Classifier: License :: OSI Approved :: BSD License
Classifier: Natural Language :: English
Classifier: Programming Language :: Python :: 3
Classifier: Programming Language :: Python :: 3.8
Classifier: Programming Language :: Python :: 3.9
Classifier: Programming Language :: Python :: 3.10
Classifier: Typing :: Typed
Requires-Python: >=3.8
Requires-Dist: lasso-3d
Requires-Dist: membrain-pick
Requires-Dist: membrain-seg
Requires-Dist: membrain-stats
Requires-Dist: napari
Requires-Dist: surforama
Provides-Extra: dev
Requires-Dist: black; extra == 'dev'
Requires-Dist: ipython; extra == 'dev'
Requires-Dist: mkdocs-material; extra == 'dev'
Requires-Dist: pdbpp; extra == 'dev'
Requires-Dist: pre-commit; extra == 'dev'
Requires-Dist: pytest; extra == 'dev'
Requires-Dist: pytest-cov; extra == 'dev'
Requires-Dist: rich; extra == 'dev'
Requires-Dist: ruff; extra == 'dev'
Provides-Extra: test
Requires-Dist: pytest-cov; extra == 'test'
Requires-Dist: pytest>=6.0; extra == 'test'
